[
  {
    "term": "用户id",
    "description": "用户id",
    "aliases": [
      "用户id",
      "user_id"
    ],
    "relatedColumns": [
      "user_id"
    ],
    "evidence": "来自字段 `user_id` 的语义注释"
  },
  {
    "term": "商家id",
    "description": "商家id",
    "aliases": [
      "商家id",
      "merchant_id"
    ],
    "relatedColumns": [
      "merchant_id"
    ],
    "evidence": "来自字段 `merchant_id` 的语义注释"
  },
  {
    "term": "商户类型code 1.急速发货商户 2.企业商户 3.认证商户 4.跨境商家 5.个人普通商户 6",
    "description": "商户类型code 1.急速发货商户 2.企业商户 3.认证商户 4.跨境商家 5.个人普通商户 6-品牌方",
    "aliases": [
      "商户类型code 1.急速发货商户 2.企业商户 3.认证商户 4.跨境商家 5.个人普通商户 6",
      "merchant_type_code",
      "商户类型code 1.急速发货商户 2.企业商户 3.认证商户 4.跨境商家 5.个人普通商户 6-品牌方"
    ],
    "relatedColumns": [
      "merchant_type_code"
    ],
    "evidence": "来自字段 `merchant_type_code` 的语义注释"
  },
  {
    "term": "商户类型name 1.急速发货商户 2.企业商户 3.认证商户 4.跨境商家 5.个人普通商户 6",
    "description": "商户类型name 1.急速发货商户 2.企业商户 3.认证商户 4.跨境商家 5.个人普通商户 6-品牌方",
    "aliases": [
      "商户类型name 1.急速发货商户 2.企业商户 3.认证商户 4.跨境商家 5.个人普通商户 6",
      "merchant_type_name",
      "商户类型name 1.急速发货商户 2.企业商户 3.认证商户 4.跨境商家 5.个人普通商户 6-品牌方"
    ],
    "relatedColumns": [
      "merchant_type_name"
    ],
    "evidence": "来自字段 `merchant_type_name` 的语义注释"
  },
  {
    "term": "资质类型code",
    "description": "资质类型code -1代表商家是服务商 0、商家入驻时填基本信息，还没填资质信息 1.品牌方 2.经销商 3.市场贸易商 4.扫货商 5.零售百货商",
    "aliases": [
      "资质类型code",
      "brand_type_code",
      "资质类型code -1代表商家是服务商 0、商家入驻时填基本信息，还没填资质信息 1.品牌方 2.经销商 3.市场贸易商 4.扫货商 5.零售百货商"
    ],
    "relatedColumns": [
      "brand_type_code"
    ],
    "evidence": "来自字段 `brand_type_code` 的语义注释"
  },
  {
    "term": "资质类型name",
    "description": "资质类型name -1代表商家是服务商 0、商家入驻时填基本信息，还没填资质信息 1.品牌方 2.经销商 3.市场贸易商 4.扫货商 5.零售百货商",
    "aliases": [
      "资质类型name",
      "brand_type_name",
      "资质类型name -1代表商家是服务商 0、商家入驻时填基本信息，还没填资质信息 1.品牌方 2.经销商 3.市场贸易商 4.扫货商 5.零售百货商"
    ],
    "relatedColumns": [
      "brand_type_name"
    ],
    "evidence": "来自字段 `brand_type_name` 的语义注释"
  },
  {
    "term": "审批人aclIds",
    "description": "审批人aclIds，逗号分隔",
    "aliases": [
      "审批人aclIds",
      "audit_user_list",
      "审批人aclIds，逗号分隔"
    ],
    "relatedColumns": [
      "audit_user_list"
    ],
    "evidence": "来自字段 `audit_user_list` 的语义注释"
  },
  {
    "term": "审核状态code",
    "description": "审核状态code，商家提交资料-0，保证金/账单/费率/协议填写审核-100，保证金低于标准，二次审核-110，初审不通过-120，初审通过，等待特批费率/类目运营审核-130，初审完成-140，待法务审核-200，法务审核不通过-210，法务审核通过，商家协议待确认-300，商家协议确认成功，保证金待缴纳-500，保证金转账待审核-520，保证金转账审核不通过-530，商家入驻被驳回-600，保证金转账审核通过，入驻完成-800",
    "aliases": [
      "审核状态code",
      "merchant_apply_status_code",
      "审核状态code，商家提交资料-0，保证金/账单/费率/协议填写审核-100，保证金低于标准，二次审核-110，初审不通过-120，初审通过，等待特批费率/类目运营审核-130，初审完成-140，待法务审核-200，法务审核不通过-210，法务审核通过，商家协议待确认-300，商家协议确认成功，保证金待缴纳-500，保证金转账待审核-520，保证金转账审核不通过-530，商家入驻被驳回-600，保证金转账审核通过，入驻完成-800"
    ],
    "relatedColumns": [
      "merchant_apply_status_code"
    ],
    "evidence": "来自字段 `merchant_apply_status_code` 的语义注释"
  },
  {
    "term": "审核状态name",
    "description": "审核状态name",
    "aliases": [
      "审核状态name",
      "merchant_apply_status_name"
    ],
    "relatedColumns": [
      "merchant_apply_status_name"
    ],
    "evidence": "来自字段 `merchant_apply_status_name` 的语义注释"
  },
  {
    "term": "商户入驻初始保证金元",
    "description": "商户入驻初始保证金元",
    "aliases": [
      "商户入驻初始保证金元",
      "init_deposit_amt"
    ],
    "relatedColumns": [
      "init_deposit_amt"
    ],
    "evidence": "来自字段 `init_deposit_amt` 的语义注释"
  },
  {
    "term": "结算类型code 0.实时 1.周结 2.半月结 3.月结",
    "description": "结算类型code 0.实时 1.周结 2.半月结 3.月结",
    "aliases": [
      "结算类型code 0.实时 1.周结 2.半月结 3.月结",
      "balance_type_code"
    ],
    "relatedColumns": [
      "balance_type_code"
    ],
    "evidence": "来自字段 `balance_type_code` 的语义注释"
  },
  {
    "term": "结算类型name 0.实时 1.周结 2.半月结 3.月结",
    "description": "结算类型name 0.实时 1.周结 2.半月结 3.月结",
    "aliases": [
      "结算类型name 0.实时 1.周结 2.半月结 3.月结",
      "balance_type_name"
    ],
    "relatedColumns": [
      "balance_type_name"
    ],
    "evidence": "来自字段 `balance_type_name` 的语义注释"
  },
  {
    "term": "商家手机号",
    "description": "商家手机号",
    "aliases": [
      "商家手机号",
      "mobile"
    ],
    "relatedColumns": [
      "mobile"
    ],
    "evidence": "来自字段 `mobile` 的语义注释"
  },
  {
    "term": "公司名称",
    "description": "公司名称",
    "aliases": [
      "公司名称",
      "company_name"
    ],
    "relatedColumns": [
      "company_name"
    ],
    "evidence": "来自字段 `company_name` 的语义注释"
  },
  {
    "term": "营业执照编号",
    "description": "营业执照编号",
    "aliases": [
      "营业执照编号",
      "license_id"
    ],
    "relatedColumns": [
      "license_id"
    ],
    "evidence": "来自字段 `license_id` 的语义注释"
  },
  {
    "term": "营业执照有效期 开始时间",
    "description": "营业执照有效期 开始时间",
    "aliases": [
      "营业执照有效期 开始时间",
      "license_period_start"
    ],
    "relatedColumns": [
      "license_period_start"
    ],
    "evidence": "来自字段 `license_period_start` 的语义注释"
  },
  {
    "term": "营业执照有效期 结束时间",
    "description": "营业执照有效期 结束时间",
    "aliases": [
      "营业执照有效期 结束时间",
      "license_period_end"
    ],
    "relatedColumns": [
      "license_period_end"
    ],
    "evidence": "来自字段 `license_period_end` 的语义注释"
  },
  {
    "term": "省",
    "description": "省",
    "aliases": [
      "省",
      "company_province"
    ],
    "relatedColumns": [
      "company_province"
    ],
    "evidence": "来自字段 `company_province` 的语义注释"
  },
  {
    "term": "市",
    "description": "市",
    "aliases": [
      "市",
      "company_city"
    ],
    "relatedColumns": [
      "company_city"
    ],
    "evidence": "来自字段 `company_city` 的语义注释"
  },
  {
    "term": "区",
    "description": "区",
    "aliases": [
      "区",
      "company_district"
    ],
    "relatedColumns": [
      "company_district"
    ],
    "evidence": "来自字段 `company_district` 的语义注释"
  },
  {
    "term": "详细地址",
    "description": "详细地址",
    "aliases": [
      "详细地址",
      "company_address"
    ],
    "relatedColumns": [
      "company_address"
    ],
    "evidence": "来自字段 `company_address` 的语义注释"
  },
  {
    "term": "法人姓名",
    "description": "法人姓名",
    "aliases": [
      "法人姓名",
      "corporation_name"
    ],
    "relatedColumns": [
      "corporation_name"
    ],
    "evidence": "来自字段 `corporation_name` 的语义注释"
  },
  {
    "term": "法人身份证号",
    "description": "法人身份证号",
    "aliases": [
      "法人身份证号",
      "corporation_idcard"
    ],
    "relatedColumns": [
      "corporation_idcard"
    ],
    "evidence": "来自字段 `corporation_idcard` 的语义注释"
  },
  {
    "term": "法人身份有效期 开始时间",
    "description": "法人身份有效期 开始时间",
    "aliases": [
      "法人身份有效期 开始时间",
      "corporation_idcard_period_start"
    ],
    "relatedColumns": [
      "corporation_idcard_period_start"
    ],
    "evidence": "来自字段 `corporation_idcard_period_start` 的语义注释"
  },
  {
    "term": "法人身份有效期 结束时间",
    "description": "法人身份有效期 结束时间",
    "aliases": [
      "法人身份有效期 结束时间",
      "corporation_idcard_period_end"
    ],
    "relatedColumns": [
      "corporation_idcard_period_end"
    ],
    "evidence": "来自字段 `corporation_idcard_period_end` 的语义注释"
  },
  {
    "term": "是否支持七天无理由退货 0 否 1 是",
    "description": "是否支持七天无理由退货 0 否 1 是",
    "aliases": [
      "是否支持七天无理由退货 0 否 1 是",
      "is_unconditional_refund"
    ],
    "relatedColumns": [
      "is_unconditional_refund"
    ],
    "evidence": "来自字段 `is_unconditional_refund` 的语义注释"
  },
  {
    "term": "是否支持开具发票 0否 1是",
    "description": "是否支持开具发票 0否 1是",
    "aliases": [
      "是否支持开具发票 0否 1是",
      "is_invoice"
    ],
    "relatedColumns": [
      "is_invoice"
    ],
    "evidence": "来自字段 `is_invoice` 的语义注释"
  },
  {
    "term": "退货地址收货人手机号",
    "description": "退货地址收货人手机号",
    "aliases": [
      "退货地址收货人手机号",
      "refund_mobile"
    ],
    "relatedColumns": [
      "refund_mobile"
    ],
    "evidence": "来自字段 `refund_mobile` 的语义注释"
  },
  {
    "term": "入驻邀约人姓名",
    "description": "入驻邀约人姓名",
    "aliases": [
      "入驻邀约人姓名",
      "inviter"
    ],
    "relatedColumns": [
      "inviter"
    ],
    "evidence": "来自字段 `inviter` 的语义注释"
  },
  {
    "term": "入驻邀约人手机号",
    "description": "入驻邀约人手机号",
    "aliases": [
      "入驻邀约人手机号",
      "inviter_mobile"
    ],
    "relatedColumns": [
      "inviter_mobile"
    ],
    "evidence": "来自字段 `inviter_mobile` 的语义注释"
  },
  {
    "term": "币种",
    "description": "币种",
    "aliases": [
      "币种",
      "currency"
    ],
    "relatedColumns": [
      "currency"
    ],
    "evidence": "来自字段 `currency` 的语义注释"
  },
  {
    "term": "发货模式code 1",
    "description": "发货模式code 1-集货模式 2-自发货模式",
    "aliases": [
      "发货模式code 1",
      "ship_model_code",
      "发货模式code 1-集货模式 2-自发货模式"
    ],
    "relatedColumns": [
      "ship_model_code"
    ],
    "evidence": "来自字段 `ship_model_code` 的语义注释"
  },
  {
    "term": "发货模式name 1",
    "description": "发货模式name 1-集货模式 2-自发货模式",
    "aliases": [
      "发货模式name 1",
      "ship_model_name",
      "发货模式name 1-集货模式 2-自发货模式"
    ],
    "relatedColumns": [
      "ship_model_name"
    ],
    "evidence": "来自字段 `ship_model_name` 的语义注释"
  },
  {
    "term": "联系人姓名",
    "description": "联系人姓名",
    "aliases": [
      "联系人姓名",
      "contact_name"
    ],
    "relatedColumns": [
      "contact_name"
    ],
    "evidence": "来自字段 `contact_name` 的语义注释"
  },
  {
    "term": "联系人身份证号",
    "description": "联系人身份证号",
    "aliases": [
      "联系人身份证号",
      "contact_idcard"
    ],
    "relatedColumns": [
      "contact_idcard"
    ],
    "evidence": "来自字段 `contact_idcard` 的语义注释"
  },
  {
    "term": "联系人身份有效期 开始时间",
    "description": "联系人身份有效期 开始时间",
    "aliases": [
      "联系人身份有效期 开始时间",
      "contact_idcard_period_start"
    ],
    "relatedColumns": [
      "contact_idcard_period_start"
    ],
    "evidence": "来自字段 `contact_idcard_period_start` 的语义注释"
  },
  {
    "term": "联系人身份有效期 结束时间",
    "description": "联系人身份有效期 结束时间",
    "aliases": [
      "联系人身份有效期 结束时间",
      "contact_idcard_period_end"
    ],
    "relatedColumns": [
      "contact_idcard_period_end"
    ],
    "evidence": "来自字段 `contact_idcard_period_end` 的语义注释"
  },
  {
    "term": "联系人默认大陆身份证",
    "description": "联系人默认大陆身份证，类型包括：100 大陆身份证；105 港澳居民往来内地通行证；106 台湾同胞往来大陆通行证；108 外国人居留证",
    "aliases": [
      "联系人默认大陆身份证",
      "contact_idcard_type",
      "联系人默认大陆身份证，类型包括：100 大陆身份证；105 港澳居民往来内地通行证；106 台湾同胞往来大陆通行证；108 外国人居留证"
    ],
    "relatedColumns": [
      "contact_idcard_type"
    ],
    "evidence": "来自字段 `contact_idcard_type` 的语义注释"
  },
  {
    "term": "联系人手机号",
    "description": "联系人手机号",
    "aliases": [
      "联系人手机号",
      "contact_mobile"
    ],
    "relatedColumns": [
      "contact_mobile"
    ],
    "evidence": "来自字段 `contact_mobile` 的语义注释"
  },
  {
    "term": "经营商省地区",
    "description": "经营商省地区",
    "aliases": [
      "经营商省地区",
      "business_province"
    ],
    "relatedColumns": [
      "business_province"
    ],
    "evidence": "来自字段 `business_province` 的语义注释"
  },
  {
    "term": "经营商所在城市地区",
    "description": "经营商所在城市地区",
    "aliases": [
      "经营商所在城市地区",
      "business_city"
    ],
    "relatedColumns": [
      "business_city"
    ],
    "evidence": "来自字段 `business_city` 的语义注释"
  },
  {
    "term": "经营商街道地区",
    "description": "经营商街道地区",
    "aliases": [
      "经营商街道地区",
      "business_district"
    ],
    "relatedColumns": [
      "business_district"
    ],
    "evidence": "来自字段 `business_district` 的语义注释"
  },
  {
    "term": "经营商详细地址",
    "description": "经营商详细地址",
    "aliases": [
      "经营商详细地址",
      "business_address"
    ],
    "relatedColumns": [
      "business_address"
    ],
    "evidence": "来自字段 `business_address` 的语义注释"
  },
  {
    "term": "发货省",
    "description": "发货省",
    "aliases": [
      "发货省",
      "send_province"
    ],
    "relatedColumns": [
      "send_province"
    ],
    "evidence": "来自字段 `send_province` 的语义注释"
  },
  {
    "term": "发货市",
    "description": "发货市",
    "aliases": [
      "发货市",
      "send_city"
    ],
    "relatedColumns": [
      "send_city"
    ],
    "evidence": "来自字段 `send_city` 的语义注释"
  },
  {
    "term": "发货区",
    "description": "发货区",
    "aliases": [
      "发货区",
      "send_district"
    ],
    "relatedColumns": [
      "send_district"
    ],
    "evidence": "来自字段 `send_district` 的语义注释"
  },
  {
    "term": "退货地址街道",
    "description": "退货地址街道",
    "aliases": [
      "退货地址街道",
      "send_street",
      "refnd_street"
    ],
    "relatedColumns": [
      "send_street",
      "refnd_street"
    ],
    "evidence": "来自字段 `send_street` 的语义注释"
  },
  {
    "term": "发货详细地址",
    "description": "发货详细地址",
    "aliases": [
      "发货详细地址",
      "send_address"
    ],
    "relatedColumns": [
      "send_address"
    ],
    "evidence": "来自字段 `send_address` 的语义注释"
  },
  {
    "term": "退货地址省",
    "description": "退货地址省",
    "aliases": [
      "退货地址省",
      "refnd_province"
    ],
    "relatedColumns": [
      "refnd_province"
    ],
    "evidence": "来自字段 `refnd_province` 的语义注释"
  },
  {
    "term": "退货地址市",
    "description": "退货地址市",
    "aliases": [
      "退货地址市",
      "refnd_city"
    ],
    "relatedColumns": [
      "refnd_city"
    ],
    "evidence": "来自字段 `refnd_city` 的语义注释"
  },
  {
    "term": "退货地址区",
    "description": "退货地址区",
    "aliases": [
      "退货地址区",
      "refnd_district"
    ],
    "relatedColumns": [
      "refnd_district"
    ],
    "evidence": "来自字段 `refnd_district` 的语义注释"
  },
  {
    "term": "退货地址详细地址",
    "description": "退货地址详细地址",
    "aliases": [
      "退货地址详细地址",
      "refnd_address"
    ],
    "relatedColumns": [
      "refnd_address"
    ],
    "evidence": "来自字段 `refnd_address` 的语义注释"
  },
  {
    "term": "协议版本",
    "description": "协议版本",
    "aliases": [
      "协议版本",
      "service_version"
    ],
    "relatedColumns": [
      "service_version"
    ],
    "evidence": "来自字段 `service_version` 的语义注释"
  },
  {
    "term": "手续费下限",
    "description": "手续费下限",
    "aliases": [
      "手续费下限",
      "min_poundage"
    ],
    "relatedColumns": [
      "min_poundage"
    ],
    "evidence": "来自字段 `min_poundage` 的语义注释"
  },
  {
    "term": "手续费上限",
    "description": "手续费上限",
    "aliases": [
      "手续费上限",
      "max_poundage"
    ],
    "relatedColumns": [
      "max_poundage"
    ],
    "evidence": "来自字段 `max_poundage` 的语义注释"
  },
  {
    "term": "开户行",
    "description": "开户行",
    "aliases": [
      "开户行",
      "bank_name"
    ],
    "relatedColumns": [
      "bank_name"
    ],
    "evidence": "来自字段 `bank_name` 的语义注释"
  },
  {
    "term": "银行账号",
    "description": "银行账号",
    "aliases": [
      "银行账号",
      "bank_account"
    ],
    "relatedColumns": [
      "bank_account"
    ],
    "evidence": "来自字段 `bank_account` 的语义注释"
  },
  {
    "term": "账户类型code 1.对公 2.对私",
    "description": "账户类型code 1.对公 2.对私",
    "aliases": [
      "账户类型code 1.对公 2.对私",
      "account_type_code"
    ],
    "relatedColumns": [
      "account_type_code"
    ],
    "evidence": "来自字段 `account_type_code` 的语义注释"
  },
  {
    "term": "账户类型name 1.对公 2.对私",
    "description": "账户类型name 1.对公 2.对私",
    "aliases": [
      "账户类型name 1.对公 2.对私",
      "account_type_name"
    ],
    "relatedColumns": [
      "account_type_name"
    ],
    "evidence": "来自字段 `account_type_name` 的语义注释"
  },
  {
    "term": "冻结保证金",
    "description": "冻结保证金",
    "aliases": [
      "冻结保证金",
      "deposit_freeze"
    ],
    "relatedColumns": [
      "deposit_freeze"
    ],
    "evidence": "来自字段 `deposit_freeze` 的语义注释"
  },
  {
    "term": "保证金",
    "description": "保证金",
    "aliases": [
      "deposit_amt",
      "保证金充值",
      "保证金补缴"
    ],
    "relatedColumns": [
      "deposit_amt"
    ],
    "evidence": "来自字段 `deposit_amt` 的语义注释"
  },
  {
    "term": "费率折扣",
    "description": "费率折扣",
    "aliases": [
      "费率折扣",
      "poundage_discount"
    ],
    "relatedColumns": [
      "poundage_discount"
    ],
    "evidence": "来自字段 `poundage_discount` 的语义注释"
  },
  {
    "term": "费率折扣开始时间",
    "description": "费率折扣开始时间",
    "aliases": [
      "费率折扣开始时间",
      "discount_start_time"
    ],
    "relatedColumns": [
      "discount_start_time"
    ],
    "evidence": "来自字段 `discount_start_time` 的语义注释"
  },
  {
    "term": "费率折扣结束时间",
    "description": "费率折扣结束时间",
    "aliases": [
      "费率折扣结束时间",
      "discount_end_time"
    ],
    "relatedColumns": [
      "discount_end_time"
    ],
    "evidence": "来自字段 `discount_end_time` 的语义注释"
  },
  {
    "term": "添加时间",
    "description": "添加时间",
    "aliases": [
      "添加时间",
      "create_time"
    ],
    "relatedColumns": [
      "create_time"
    ],
    "evidence": "来自字段 `create_time` 的语义注释"
  },
  {
    "term": "修改时间",
    "description": "修改时间",
    "aliases": [
      "修改时间",
      "modify_time"
    ],
    "relatedColumns": [
      "modify_time"
    ],
    "evidence": "来自字段 `modify_time` 的语义注释"
  },
  {
    "term": "日期分区yyyyMMdd",
    "description": "日期分区yyyyMMdd",
    "aliases": [
      "日期分区yyyyMMdd",
      "pt"
    ],
    "relatedColumns": [
      "pt"
    ],
    "evidence": "来自字段 `pt` 的语义注释"
  },
  {
    "term": "商家档案",
    "description": "商家主体、资质、结算、保证金和发货模式等基础信息",
    "aliases": [
      "商家信息",
      "主体信息",
      "入驻信息"
    ],
    "relatedColumns": [],
    "evidence": "由表名/字段语义自动沉淀"
  }
]
